juno/__init__.py
django_juno-0.0.7.dist-info/LICENSE
django_juno-0.0.7.dist-info/METADATA
django_juno-0.0.7.dist-info/WHEEL
django_juno-0.0.7.dist-info/top_level.txt
django_juno-0.0.7.dist-info/RECORD
