Metadata-Version: 2.1
Name: django-juno
Version: 0.0.7
Summary: Integração da Juno com Django
Home-page: https://github.com/alessandrak/django-juno
Author: Alessandra Carneiro
Author-email: alessandra@rd2.ventures
License: MIT License
Platform: UNKNOWN
Classifier: Programming Language :: Python :: 3
Classifier: Framework :: Django :: 3.1
Classifier: License :: OSI Approved :: MIT License
Classifier: Operating System :: OS Independent
Requires-Python: >=3.7
